sample_sdk/__init__.py
sample_sdk/main.py
sample_sdk/py.typed
sample_sdk-0.1.4.dist-info/METADATA
sample_sdk-0.1.4.dist-info/WHEEL
sample_sdk-0.1.4.dist-info/RECORD
