Metadata-Version: 2.4
Name: sample-sdk
Version: 0.1.4
Summary: This is a sample project
Author-email: swapna <swapna.s@gadgetsoftware.com>
Requires-Python: >=3.13
Requires-Dist: python-dotenv>=1.1.1
